costra/__init__.py
costra/costra.py
costra/data/data.tsv
costra-1.1.dist-info/METADATA
costra-1.1.dist-info/WHEEL
costra-1.1.dist-info/top_level.txt
costra-1.1.dist-info/RECORD
