Metadata-Version: 2.1
Name: costra
Version: 1.1
Home-page: https://github.com/barancik/costra
Author: Petra Barancikova
Author-email: barancikova@ufal.mff.cuni.cz
License: Creative Commons Attribution-Noncommercial-Share Alike license
Keywords: embeddings evaluation
Requires-Python: >=3.5, <4
Requires-Dist: numpy
